thumbor/__init__.py
thumbor/app.py
thumbor/config.py
thumbor/console.py
thumbor/context.py
thumbor/crypto.py
thumbor/doctor.py
thumbor/importer.py
thumbor/point.py
thumbor/server.py
thumbor/signal_handler.py
thumbor/testing.py
thumbor/threadpool.py
thumbor/thumbor.conf
thumbor/transformer.py
thumbor/url.py
thumbor/url_composer.py
thumbor/utils.py
thumbor/detectors/__init__.py
thumbor/detectors/local_detector.py
thumbor/detectors/face_detector/__init__.py
thumbor/detectors/face_detector/haarcascade_frontalface_alt.xml
thumbor/detectors/face_detector/haarcascade_frontalface_alt2.xml
thumbor/detectors/face_detector/haarcascade_frontalface_alt_tree.xml
thumbor/detectors/face_detector/haarcascade_frontalface_default.xml
thumbor/detectors/feature_detector/__init__.py
thumbor/detectors/glasses_detector/__init__.py
thumbor/detectors/glasses_detector/haarcascade_eye_tree_eyeglasses.xml
thumbor/detectors/primary_color_detector/__init__.py
thumbor/detectors/profile_detector/__init__.py
thumbor/detectors/profile_detector/haarcascade_profileface.xml
thumbor/detectors/queued_detector/__init__.py
thumbor/detectors/queued_detector/queued_complete_detector.py
thumbor/detectors/queued_detector/queued_face_detector.py
thumbor/detectors/queued_detector/queued_feature_detector.py
thumbor/detectors/queued_sqs_detector/__init__.py
thumbor/engines/__init__.py
thumbor/engines/gif.py
thumbor/engines/json_engine.py
thumbor/engines/pil.py
thumbor/engines/extensions/__init__.py
thumbor/engines/extensions/exif_orientation_editor.py
thumbor/engines/extensions/pil.py
thumbor/error_handlers/__init__.py
thumbor/error_handlers/file.py
thumbor/error_handlers/sentry.py
thumbor/ext/__init__.py
thumbor/ext/filters/__init__.py
thumbor/ext/filters/_alpha.c
thumbor/ext/filters/_alpha.so
thumbor/ext/filters/_bounding_box.c
thumbor/ext/filters/_bounding_box.so
thumbor/ext/filters/_brightness.c
thumbor/ext/filters/_brightness.so
thumbor/ext/filters/_colorize.c
thumbor/ext/filters/_colorize.so
dffrntlab_thumbor-7.2.1.dist-info/LICENSE
dffrntlab_thumbor-7.2.1.dist-info/METADATA
dffrntlab_thumbor-7.2.1.dist-info/WHEEL
dffrntlab_thumbor-7.2.1.dist-info/entry_points.txt
dffrntlab_thumbor-7.2.1.dist-info/top_level.txt
dffrntlab_thumbor-7.2.1.dist-info/RECORD
